{"id":1814,"name":"DrawerElement","kind":4194304,"kindString":"Type alias","flags":{},"children":[],"sources":[{"fileName":"src/frontend/YafElementDrawers.ts","fullFileName":"/home/runner/work/typedoc-theme-yaf/typedoc-theme-yaf/src/frontend/YafElementDrawers.ts","line":10,"character":12,"url":"https://github.com/citkane/typedoc-theme-yaf/blob/967d756/src/frontend/YafElementDrawers.ts#L10"}],"type":{"type":"intersection","types":[{"type":"reference","name":"HTMLElement","qualifiedName":"HTMLElement","package":"typescript"},{"type":"reference","id":1815,"name":"YafElementDrawers"}]},"is":{"declaration":true},"location":{"query":"frontend.TypeAlias.DrawerElement","hash":""},"text":{},"parentId":2}
