{"id":1985,"name":"hierarchy","kind":4194304,"kindString":"Type alias","flags":{},"children":[],"sources":[{"fileName":"src/types/types.ts","fullFileName":"/home/runner/work/typedoc-theme-yaf/typedoc-theme-yaf/src/types/types.ts","line":82,"character":12,"url":"https://github.com/citkane/typedoc-theme-yaf/blob/30de432/src/types/types.ts#L82"}],"type":{"type":"reflection","declaration":{"id":1986,"name":"hierarchy","kind":65536,"kindString":"Type literal","flags":{},"children":[{"id":1990,"name":"children","kind":1024,"kindString":"Property","flags":{"isOptional":true},"sources":[{"fileName":"src/types/types.ts","fullFileName":"/home/runner/work/typedoc-theme-yaf/typedoc-theme-yaf/src/types/types.ts","line":86,"character":1,"url":"https://github.com/citkane/typedoc-theme-yaf/blob/30de432/src/types/types.ts#L86"}],"type":{"type":"array","elementType":{"type":"reference","id":1985,"name":"hierarchy"}},"is":{"declaration":true},"location":{"query":"types.common.TypeAlias.hierarchy","hash":"children"},"text":{},"parentId":1985},{"id":1989,"name":"isTarget","kind":1024,"kindString":"Property","flags":{"isOptional":true},"sources":[{"fileName":"src/types/types.ts","fullFileName":"/home/runner/work/typedoc-theme-yaf/typedoc-theme-yaf/src/types/types.ts","line":85,"character":1,"url":"https://github.com/citkane/typedoc-theme-yaf/blob/30de432/src/types/types.ts#L85"}],"type":{"type":"intrinsic","name":"boolean"},"is":{"declaration":true},"location":{"query":"types.common.TypeAlias.hierarchy","hash":"isTarget"},"text":{},"parentId":1985},{"id":1988,"name":"linkId","kind":1024,"kindString":"Property","flags":{"isOptional":true},"sources":[{"fileName":"src/types/types.ts","fullFileName":"/home/runner/work/typedoc-theme-yaf/typedoc-theme-yaf/src/types/types.ts","line":84,"character":1,"url":"https://github.com/citkane/typedoc-theme-yaf/blob/30de432/src/types/types.ts#L84"}],"type":{"type":"intrinsic","name":"string"},"is":{"declaration":true},"location":{"query":"types.common.TypeAlias.hierarchy","hash":"linkId"},"text":{},"parentId":1985},{"id":1987,"name":"name","kind":1024,"kindString":"Property","flags":{},"sources":[{"fileName":"src/types/types.ts","fullFileName":"/home/runner/work/typedoc-theme-yaf/typedoc-theme-yaf/src/types/types.ts","line":83,"character":1,"url":"https://github.com/citkane/typedoc-theme-yaf/blob/30de432/src/types/types.ts#L83"}],"type":{"type":"intrinsic","name":"string"},"is":{"declaration":true},"location":{"query":"types.common.TypeAlias.hierarchy","hash":"name"},"text":{},"parentId":1985}],"groups":[{"title":"Properties","children":[1990,1989,1988,1987]}],"sources":[{"fileName":"src/types/types.ts","line":82,"character":24,"url":"https://github.com/citkane/typedoc-theme-yaf/blob/30de432/src/types/types.ts#L82"}],"location":{"query":"types.common.TypeAlias.hierarchy","hash":""}}},"is":{"declaration":true},"location":{"query":"types.common.TypeAlias.hierarchy","hash":""},"text":{},"parentId":1929}
