{"id":1798,"name":"reflection","kind":32,"kindString":"Variable","flags":{"isConst":true},"comment":{"summary":[{"kind":"text","text":"An example object"}]},"children":[],"sources":[{"fileName":"src/examples/reflection.ts","line":7,"character":13,"url":"https://github.com/citkane/typedoc-theme-yaf/blob/d8b28e5/src/examples/reflection.ts#L7"}],"type":{"type":"reflection","declaration":{"id":1799,"name":"reflection","kind":65536,"kindString":"Type literal","flags":{},"children":[{"id":1802,"name":"func2","kind":4096,"kindString":"Property","flags":{},"sources":[{"fileName":"src/examples/reflection.ts","line":15,"character":1,"url":"https://github.com/citkane/typedoc-theme-yaf/blob/d8b28e5/src/examples/reflection.ts#L15"}],"type":{"type":"reflection","declaration":{"id":1803,"name":"func2","kind":65536,"kindString":"Type literal","flags":{},"sources":[{"fileName":"src/examples/reflection.ts","line":15,"character":8,"url":"https://github.com/citkane/typedoc-theme-yaf/blob/d8b28e5/src/examples/reflection.ts#L15"}],"signatures":[{"id":1804,"name":"func2","kind":4096,"kindString":"Call signature","flags":{},"comment":{"summary":[{"kind":"text","text":"A comment on a reflection child"}],"blockTags":[{"tag":"@returns","content":[]}]},"type":{"type":"intrinsic","name":"void"},"is":{"declaration":false},"location":{"query":"examples.Variable.reflection","hash":"func2.__type"},"text":{"comment":"<p>A comment on a reflection child</p>\n<h5>Returns:</h5>"},"parentId":1798}],"location":{"query":"examples.Variable.reflection","hash":"func2"}}},"defaultValue":"...","is":{"declaration":true},"location":{"query":"examples.Variable.reflection","hash":"func2"},"text":{},"parentId":1798},{"id":1805,"name":"func3","kind":4096,"kindString":"Property","flags":{},"sources":[{"fileName":"src/examples/reflection.ts","line":16,"character":1,"url":"https://github.com/citkane/typedoc-theme-yaf/blob/d8b28e5/src/examples/reflection.ts#L16"}],"type":{"type":"reflection","declaration":{"id":1806,"name":"func3","kind":65536,"kindString":"Type literal","flags":{},"sources":[{"fileName":"src/examples/reflection.ts","line":16,"character":8,"url":"https://github.com/citkane/typedoc-theme-yaf/blob/d8b28e5/src/examples/reflection.ts#L16"}],"signatures":[{"id":1807,"name":"func3","kind":4096,"kindString":"Call signature","flags":{},"typeParameter":[{"id":1808,"name":"T","kind":131072,"kindString":"Type parameter","flags":{}}],"parameters":[{"id":1809,"name":"a","kind":32768,"kindString":"Parameter","flags":{},"type":{"type":"reference","id":1808,"name":"T"},"text":{}}],"type":{"type":"reference","id":1808,"name":"T"},"is":{"declaration":false},"location":{"query":"examples.Variable.reflection","hash":"func3.__type"},"text":{},"parentId":1798}],"location":{"query":"examples.Variable.reflection","hash":"func3"}}},"defaultValue":"...","is":{"declaration":true},"location":{"query":"examples.Variable.reflection","hash":"func3"},"text":{},"parentId":1798},{"id":1813,"name":"nested","kind":1024,"kindString":"Property","flags":{},"sources":[{"fileName":"src/examples/reflection.ts","line":20,"character":1,"url":"https://github.com/citkane/typedoc-theme-yaf/blob/d8b28e5/src/examples/reflection.ts#L20"}],"type":{"type":"reflection","declaration":{"id":1814,"name":"nested","kind":65536,"kindString":"Type literal","flags":{},"children":[{"id":1815,"name":"nestedProp","kind":1024,"kindString":"Property","flags":{},"comment":{"summary":[{"kind":"text","text":"A nested property"}]},"sources":[{"fileName":"src/examples/reflection.ts","line":24,"character":2,"url":"https://github.com/citkane/typedoc-theme-yaf/blob/d8b28e5/src/examples/reflection.ts#L24"}],"type":{"type":"intrinsic","name":"string"},"defaultValue":"'Im a nested prop!'","is":{"declaration":true},"location":{"query":"examples.Variable.reflection","hash":"nested.nestedProp"},"text":{"comment":"<p>A nested property</p>\n"},"parentId":1798},{"id":1818,"name":"nestedReflection","kind":1024,"kindString":"Property","flags":{},"sources":[{"fileName":"src/examples/reflection.ts","line":28,"character":2,"url":"https://github.com/citkane/typedoc-theme-yaf/blob/d8b28e5/src/examples/reflection.ts#L28"}],"type":{"type":"reflection","declaration":{"id":1819,"name":"nestedReflection","kind":65536,"kindString":"Type literal","flags":{},"children":[{"id":1820,"name":"prop","kind":1024,"kindString":"Property","flags":{},"sources":[{"fileName":"src/examples/reflection.ts","line":29,"character":3,"url":"https://github.com/citkane/typedoc-theme-yaf/blob/d8b28e5/src/examples/reflection.ts#L29"}],"type":{"type":"intrinsic","name":"string"},"defaultValue":"'Im a prop!'","is":{"declaration":true},"location":{"query":"examples.Variable.reflection","hash":"nested.nestedReflection.prop"},"text":{},"parentId":1798}],"groups":[{"title":"Properties","children":[1820]}],"sources":[{"fileName":"src/examples/reflection.ts","line":28,"character":20,"url":"https://github.com/citkane/typedoc-theme-yaf/blob/d8b28e5/src/examples/reflection.ts#L28"}],"location":{"query":"examples.Variable.reflection","hash":"nested.nestedReflection"}}},"defaultValue":"...","is":{"declaration":true},"location":{"query":"examples.Variable.reflection","hash":"nested.nestedReflection"},"text":{},"parentId":1798},{"id":1816,"name":"nestedFunc","kind":2048,"kindString":"Method","flags":{},"sources":[{"fileName":"src/examples/reflection.ts","line":25,"character":2,"url":"https://github.com/citkane/typedoc-theme-yaf/blob/d8b28e5/src/examples/reflection.ts#L25"}],"signatures":[{"id":1817,"name":"nestedFunc","kind":4096,"kindString":"Call signature","flags":{},"type":{"type":"intrinsic","name":"void"},"is":{"declaration":false},"location":{"query":"examples.Variable.reflection","hash":"nested.nestedFunc.nestedFunc"},"text":{},"parentId":1798}],"is":{"declaration":true},"location":{"query":"examples.Variable.reflection","hash":"nested.nestedFunc"},"text":{},"parentId":1798}],"groups":[{"title":"Properties","children":[1815,1818]},{"title":"Methods","children":[1816]}],"sources":[{"fileName":"src/examples/reflection.ts","line":20,"character":9,"url":"https://github.com/citkane/typedoc-theme-yaf/blob/d8b28e5/src/examples/reflection.ts#L20"}],"location":{"query":"examples.Variable.reflection","hash":"nested"}}},"defaultValue":"...","is":{"declaration":true},"location":{"query":"examples.Variable.reflection","hash":"nested"},"text":{},"parentId":1798},{"id":1810,"name":"prop","kind":1024,"kindString":"Property","flags":{},"sources":[{"fileName":"src/examples/reflection.ts","line":17,"character":1,"url":"https://github.com/citkane/typedoc-theme-yaf/blob/d8b28e5/src/examples/reflection.ts#L17"}],"type":{"type":"intrinsic","name":"string"},"defaultValue":"'Im a prop!'","is":{"declaration":true},"location":{"query":"examples.Variable.reflection","hash":"prop"},"text":{},"parentId":1798},{"id":1811,"name":"prop2","kind":1024,"kindString":"Property","flags":{},"sources":[{"fileName":"src/examples/reflection.ts","line":18,"character":1,"url":"https://github.com/citkane/typedoc-theme-yaf/blob/d8b28e5/src/examples/reflection.ts#L18"}],"type":{"type":"intrinsic","name":"number"},"defaultValue":"2","is":{"declaration":true},"location":{"query":"examples.Variable.reflection","hash":"prop2"},"text":{},"parentId":1798},{"id":1812,"name":"prop3","kind":1024,"kindString":"Property","flags":{},"sources":[{"fileName":"src/examples/reflection.ts","line":19,"character":1,"url":"https://github.com/citkane/typedoc-theme-yaf/blob/d8b28e5/src/examples/reflection.ts#L19"}],"type":{"type":"intrinsic","name":"string"},"defaultValue":"...","is":{"declaration":true},"location":{"query":"examples.Variable.reflection","hash":"prop3"},"text":{},"parentId":1798},{"id":1800,"name":"func","kind":2048,"kindString":"Method","flags":{},"sources":[{"fileName":"src/examples/reflection.ts","line":8,"character":1,"url":"https://github.com/citkane/typedoc-theme-yaf/blob/d8b28e5/src/examples/reflection.ts#L8"}],"signatures":[{"id":1801,"name":"func","kind":4096,"kindString":"Call signature","flags":{},"type":{"type":"intrinsic","name":"void"},"is":{"declaration":false},"location":{"query":"examples.Variable.reflection","hash":"func.func"},"text":{},"parentId":1798}],"is":{"declaration":true},"location":{"query":"examples.Variable.reflection","hash":"func"},"text":{},"parentId":1798}],"groups":[{"title":"Properties","children":[1813,1810,1811,1812]},{"title":"Methods","children":[1800,1802,1805]}],"sources":[{"fileName":"src/examples/reflection.ts","line":7,"character":26,"url":"https://github.com/citkane/typedoc-theme-yaf/blob/d8b28e5/src/examples/reflection.ts#L7"}],"location":{"query":"examples.Variable.reflection","hash":""}}},"defaultValue":"...","is":{"declaration":true},"location":{"query":"examples.Variable.reflection","hash":""},"text":{"comment":"<p>An example object</p>\n"},"parentId":3}
